whyshift/__init__.py
whyshift/algorithm.py
whyshift/dataset.py
whyshift/disde.py
whyshift/folktables_utils.py
whyshift/region_analysis.py
whyshift/utils.py
whyshift/folktables/__init__.py
whyshift/folktables/acs.py
whyshift/folktables/dataset.py
whyshift/folktables/exceptions.py
whyshift/folktables/folktables.py
whyshift/folktables/load_acs.py
whyshift/folktables/utils/__init__.py
whyshift/folktables/utils/download_utils.py
whyshift/folktables/utils/files_resources.py
whyshift/folktables/utils/load_utils.py
whyshift/methods/__init__.py
whyshift/methods/marginal_dro_criterion.py
whyshift/methods/model_family.py
whyshift/methods/model_util.py
whyshift/methods/robust_loss.py
whyshift-0.1.3.dist-info/LICENSE
whyshift-0.1.3.dist-info/METADATA
whyshift-0.1.3.dist-info/WHEEL
whyshift-0.1.3.dist-info/top_level.txt
whyshift-0.1.3.dist-info/RECORD
