Metadata-Version: 2.1
Name: whyshift
Version: 0.1.3
Summary: A package of various specified distribution shift patterns of out-of-distributoin generalization problem on tabular data, and tools for diagnosing model performance are integrated.
Home-page: https://github.com/namkoong-lab/whyshift
Author: Jiashuo Liu, Tianyu Wang, Peng Cui, Hongseok Namkoong
Author-email: liujiashuo77@gmail.com, tw2837@columbia.edu, cuip@tsinghua.edu.cn, namkoong@gsb.columbia.edu
Classifier: Programming Language :: Python :: 3
Classifier: License :: OSI Approved :: MIT License
Classifier: Operating System :: MacOS
Classifier: Operating System :: POSIX :: Linux
Requires-Python: >=3
License-File: LICENSE
Requires-Dist: pandas
Requires-Dist: numpy
Requires-Dist: scikit-learn
Requires-Dist: lightgbm
Requires-Dist: xgboost
Requires-Dist: fairlearn
Requires-Dist: tqdm
Requires-Dist: torch
Requires-Dist: scipy
